{"version":"1.2.4b","title":"Frozen Mansion of the Shadow Savant","story":"After being destroyed in a great battle centuries ago the mansion of the Shadow Savant remained abandoned. Recently a fearsome wyvern has made its home here.","rects":[{"x":-1,"y":-7,"w":3,"h":7},{"x":-3,"y":-1,"w":1,"h":1},{"x":3,"y":-1,"w":1,"h":1},{"x":-3,"y":-3,"w":1,"h":1},{"x":-3,"y":1,"w":1,"h":1},{"x":3,"y":1,"w":1,"h":1},{"x":-6,"y":-4,"w":2,"h":3},{"x":-6,"y":0,"w":2,"h":3},{"x":5,"y":0,"w":2,"h":3},{"x":-12,"y":-5,"w":5,"h":5,"rotunda":true,"ending":true},{"x":8,"y":-1,"w":5,"h":5,"rotunda":true},{"x":0,"y":0,"w":1,"h":1},{"x":-2,"y":-1,"w":1,"h":1},{"x":2,"y":-1,"w":1,"h":1},{"x":-3,"y":-2,"w":1,"h":1},{"x":-3,"y":0,"w":1,"h":1},{"x":3,"y":0,"w":1,"h":1},{"x":-4,"y":-3,"w":1,"h":1},{"x":-4,"y":1,"w":1,"h":1},{"x":4,"y":1,"w":1,"h":1},{"x":-7,"y":-3,"w":1,"h":1},{"x":7,"y":1,"w":1,"h":1},{"x":-6,"y":-1,"w":1,"h":1}],"doors":[{"x":0,"y":0,"dir":{"x":0,"y":-1},"type":3},{"x":-2,"y":-1,"dir":{"x":-1,"y":0},"type":2},{"x":2,"y":-1,"dir":{"x":1,"y":0},"type":9},{"x":-3,"y":-2,"dir":{"x":0,"y":-1},"type":9},{"x":-3,"y":0,"dir":{"x":0,"y":1},"type":9},{"x":3,"y":0,"dir":{"x":0,"y":1},"type":9},{"x":-4,"y":-3,"dir":{"x":-1,"y":0},"type":1},{"x":-4,"y":1,"dir":{"x":-1,"y":0},"type":1},{"x":4,"y":1,"dir":{"x":1,"y":0},"type":9},{"x":-7,"y":-3,"dir":{"x":-1,"y":0},"type":5},{"x":7,"y":1,"dir":{"x":1,"y":0},"type":9},{"x":-6,"y":-1,"dir":{"x":0,"y":1},"type":1}],"notes":[{"text":"A mouth-shaped ironbound door with a keyhole on the western wall of the small chamber.","ref":"1","pos":{"x":-5,"y":-2.5}},{"text":"A bird-shaped key in a glass display case.","ref":"2","pos":{"x":-5,"y":1.5}},{"text":"A chest with some gold and an enchanted glaive in it.","ref":"3","pos":{"x":10.5,"y":1.5}}],"columns":[],"water":[]}